omf_sample_library_preview/__init__.py
omf_sample_library_preview/Client/ADHOMFClient.py
omf_sample_library_preview/Client/Authentication.py
omf_sample_library_preview/Client/EDSOMFClient.py
omf_sample_library_preview/Client/OMFClient.py
omf_sample_library_preview/Client/OMFClients.py
omf_sample_library_preview/Client/OMFError.py
omf_sample_library_preview/Client/PIOMFClient.py
omf_sample_library_preview/Client/__init__.py
omf_sample_library_preview/Converters/ClassToOMFTypeConverter.py
omf_sample_library_preview/Converters/__init__.py
omf_sample_library_preview/Models/OMFClassification.py
omf_sample_library_preview/Models/OMFContainer.py
omf_sample_library_preview/Models/OMFData.py
omf_sample_library_preview/Models/OMFEnum.py
omf_sample_library_preview/Models/OMFEnumType.py
omf_sample_library_preview/Models/OMFEnumValue.py
omf_sample_library_preview/Models/OMFExtrapolationMode.py
omf_sample_library_preview/Models/OMFFormatCode.py
omf_sample_library_preview/Models/OMFInterpolationMode.py
omf_sample_library_preview/Models/OMFLinkData.py
omf_sample_library_preview/Models/OMFLinkSource.py
omf_sample_library_preview/Models/OMFLinkTarget.py
omf_sample_library_preview/Models/OMFLinkValue.py
omf_sample_library_preview/Models/OMFMessageAction.py
omf_sample_library_preview/Models/OMFMessageType.py
omf_sample_library_preview/Models/OMFType.py
omf_sample_library_preview/Models/OMFTypeCode.py
omf_sample_library_preview/Models/OMFTypeProperty.py
omf_sample_library_preview/Models/OMFTypeType.py
omf_sample_library_preview/Models/Serializeable.py
omf_sample_library_preview/Models/__init__.py
omf_sample_library_preview/Services/ContainerService.py
omf_sample_library_preview/Services/DataService.py
omf_sample_library_preview/Services/GeneralService.py
omf_sample_library_preview/Services/TypeService.py
omf_sample_library_preview/Services/__init__.py
omf_sample_library_preview/Tests/__init__.py
omf_sample_library_preview/Tests/conftest.py
omf_sample_library_preview-0.1.2rc0.dist-info/LICENSE
omf_sample_library_preview-0.1.2rc0.dist-info/METADATA
omf_sample_library_preview-0.1.2rc0.dist-info/WHEEL
omf_sample_library_preview-0.1.2rc0.dist-info/top_level.txt
omf_sample_library_preview-0.1.2rc0.dist-info/RECORD
