Metadata-Version: 2.1
Name: omf-sample-library-preview
Version: 0.1.2rc0
Summary: A preview of an OMF client library
Home-page: https://github.com/aveva/sample-omf_library_preview-python
Author: AVEVA
Author-email: samples@aveva.com
License: Apache 2.0
Platform: UNKNOWN
Classifier: Programming Language :: Python :: 3
Classifier: License :: OSI Approved :: Apache Software License
Classifier: Operating System :: OS Independent
Requires-Python: >=3.7
Requires-Dist: python-dateutil (>=2.8.2)
Requires-Dist: requests (>=2.28.2)
